wallet_fetcher/__init__.py
wallet_fetcher/main.py
wallet_fetcher-0.1.0.dist-info/LICENSE.txt
wallet_fetcher-0.1.0.dist-info/METADATA
wallet_fetcher-0.1.0.dist-info/WHEEL
wallet_fetcher-0.1.0.dist-info/top_level.txt
wallet_fetcher-0.1.0.dist-info/RECORD
